string_utils/__init__.py
string_utils/__main__.py
string_utils/core.py
stringutilslib-0.1.0.dist-info/licenses/LICENSE
stringutilslib-0.1.0.dist-info/METADATA
stringutilslib-0.1.0.dist-info/WHEEL
stringutilslib-0.1.0.dist-info/entry_points.txt
stringutilslib-0.1.0.dist-info/top_level.txt
stringutilslib-0.1.0.dist-info/RECORD
