Metadata-Version: 2.4
Name: StringUtilsLib
Version: 0.1.0
Summary: Text utilities: reverse, count letters and words
Author: Raghed Ehap Suif Alfaghe
Author-email: Raghed Ehap Suif Alfaghe <raralasaly2006@gmail.com>
License: 
Requires-Python: >=3.13
License-File: LICENSE
Dynamic: author
Dynamic: license-file
Dynamic: requires-python
